[
    {
        "added_on": "2020-11-29",
        "repeated_added_on": [],
        "categories": [
            "linux",
            "programming",
            "python",
            "systemd"
        ],
        "type": "url",
        "value": "https://github.com/torfsen/python-systemd-tutorial"
    },
    {
        "added_on": "2020-11-21",
        "repeated_added_on": [
            "2020-11-29"
        ],
        "categories": [
            "linux",
            "programming"
        ],
        "type": "factoid",
        "value": "`kill` takes readable arguments. Use `kill -KILL` or `kill -TSTP` instead of the numbers."
    },
    {
        "added_on": "2019-11-28",
        "repeated_added_on": [
            "2020-11-29"
        ],
        "categories": [
            "programming",
            "toml",
            "files"
        ],
        "type": "url",
        "value": "https://toml.io/en/",
        "title": "TOML: Tom's Obvious Minimal Language"
    }
]
